napari_bil_data_viewer/__init__.py
napari_bil_data_viewer/_version.py
napari_bil_data_viewer/bil_data_loader_widget.py
napari_bil_data_viewer/dataset_imginfo.json
napari_bil_data_viewer/dataset_info.py
napari_bil_data_viewer/dataset_info_screen.py
napari_bil_data_viewer/dataset_metadata.py
napari_bil_data_viewer/fMOST_datasets.py
napari_bil_data_viewer/fMOST_swc.py
napari_bil_data_viewer/reader.py
napari_bil_data_viewer/_tests/__init__.py
napari_bil_data_viewer/_tests/test_reader.py
napari_bil_data_viewer/resources/bil_logo.png
napari_bil_data_viewer/resources/loading.gif
napari_bil_data_viewer-0.6.0.dist-info/LICENSE
napari_bil_data_viewer-0.6.0.dist-info/METADATA
napari_bil_data_viewer-0.6.0.dist-info/WHEEL
napari_bil_data_viewer-0.6.0.dist-info/entry_points.txt
napari_bil_data_viewer-0.6.0.dist-info/top_level.txt
napari_bil_data_viewer-0.6.0.dist-info/RECORD
