Metadata-Version: 2.1
Name: napari-bil-data-viewer
Version: 0.6.0
Summary: Napari plugin for viewing Brain Image Library datasets
Home-page: https://github.com/brain-image-library/napari-bil-data-viewer
Author: Alan M Watson
Author-email: alan.watson@pitt.edu
License: BSD-3-Clause
Project-URL: Bug Tracker, https://github.com/brain-image-library/napari-bil-data-viewer/issues
Project-URL: Documentation, https://github.com/brain-image-library/napari-bil-data-viewer#README.md
Project-URL: Source Code, https://github.com/brain-image-library/napari-bil-data-viewer
Project-URL: User Support, https://github.com/brain-image-library/napari-bil-data-viewer
Classifier: Development Status :: 2 - Pre-Alpha
Classifier: Intended Audience :: Developers
Classifier: Framework :: napari
Classifier: Topic :: Software Development :: Testing
Classifier: Programming Language :: Python
Classifier: Programming Language :: Python :: 3
Classifier: Programming Language :: Python :: 3.8
Classifier: Programming Language :: Python :: 3.9
Classifier: Operating System :: OS Independent
Classifier: License :: OSI Approved :: BSD License
Requires-Python: >=3.8
License-File: LICENSE
Requires-Dist: napari[all]
Requires-Dist: napari-plugin-engine >=0.1.4
Requires-Dist: scikit-image
Requires-Dist: fsspec
Requires-Dist: requests
Requires-Dist: aiohttp
Requires-Dist: imagecodecs
Requires-Dist: beautifulsoup4
Requires-Dist: dask
Requires-Dist: neurom ==3.2.2
Requires-Dist: napari-ome-zarr ==0.5.2
